md_pkb/__init__.py
md_pkb/main.py
md_pkb/playground.py
md_pkb/routers/__init__.py
md_pkb/routers/browse.py
md_pkb/routers/misc.py
md_pkb/routers/search.py
md_pkb/templates/body
md_pkb/templates/error
md_pkb/templates/file
md_pkb/templates/folder
md_pkb/templates/header
md_pkb/templates/html
md_pkb/templates/style
md_pkb/utils/__init__.py
md_pkb/utils/app.py
md_pkb/utils/cache.py
md_pkb/utils/file_monitor.py
md_pkb/utils/files.py
md_pkb/utils/logging.py
md_pkb/utils/search.py
md_pkb-0.1.2.dist-info/METADATA
md_pkb-0.1.2.dist-info/WHEEL
md_pkb-0.1.2.dist-info/RECORD
